fengchao/__init__.py
fengchao/__version__.py
fengchao/comments.py
fengchao/core.py
fengchao/examples.py
fengchao/protocol.py
fengchao/utils.py
fengchao-2.5.1.dist-info/LICENSE
fengchao-2.5.1.dist-info/METADATA
fengchao-2.5.1.dist-info/WHEEL
fengchao-2.5.1.dist-info/top_level.txt
fengchao-2.5.1.dist-info/RECORD
