Metadata-Version: 2.1
Name: fengchao
Version: 2.5.1
Summary: 大模型框架服务调用SDK.
Home-page: 
Author: ijiwei
Author-email: 
License: MIT
Classifier: License :: OSI Approved :: MIT License
Classifier: Programming Language :: Python
Classifier: Programming Language :: Python :: 3
Classifier: Programming Language :: Python :: 3.6
Classifier: Programming Language :: Python :: 3.7
Classifier: Programming Language :: Python :: 3.8
Classifier: Programming Language :: Python :: 3.9
Classifier: Programming Language :: Python :: 3.10
Classifier: Programming Language :: Python :: Implementation :: CPython
Classifier: Programming Language :: Python :: Implementation :: PyPy
Requires-Python: >=3.6.0
License-File: LICENSE
Requires-Dist: requests ==2.31.0
Requires-Dist: pyJWT ==2.8.0
Requires-Dist: pydantic ==2.6.1
Requires-Dist: tenacity ==8.2.3
Requires-Dist: loguru
